pycregex/__init__.py
pycregex/stub.so
pycregex-2.0.4.dist-info/licenses/COPYING
pycregex-2.0.4.dist-info/METADATA
pycregex-2.0.4.dist-info/WHEEL
pycregex-2.0.4.dist-info/top_level.txt
pycregex-2.0.4.dist-info/RECORD
