Metadata-Version: 2.4
Name: pycregex
Version: 2.0.4
Summary: An implementation of POSIX regex in Python
Author-email: Nikolaos Chatzikonstantinou <nchatz314@gmail.com>
License-Expression: GPL-3.0-or-later
Project-URL: Homepage, https://codeberg.org/annoyingusername/pycregex/
Project-URL: Issues, https://codeberg.org/annoyingusername/pycregex/issues
Classifier: Programming Language :: Python :: 3
Classifier: Operating System :: OS Independent
Requires-Python: >=3.8
License-File: COPYING
Provides-Extra: tests
Requires-Dist: pytest; extra == "tests"
Dynamic: license-file
